chain_harvester/__init__.py
chain_harvester/adapters/__init__.py
chain_harvester/adapters/alchemy.py
chain_harvester/adapters/alchemy_chain.py
chain_harvester/adapters/defillama.py
chain_harvester/adapters/morpho.py
chain_harvester/adapters/sink.py
chain_harvester/api.py
chain_harvester/chain.py
chain_harvester/chainlink/__init__.py
chain_harvester/chainlink/chainlink.py
chain_harvester/chainlink/exceptions.py
chain_harvester/chainlink/mappings/__init__.py
chain_harvester/chainlink/mappings/arbitrum.py
chain_harvester/chainlink/mappings/base.py
chain_harvester/chainlink/mappings/ethereum.py
chain_harvester/chainlink/mappings/gnosis.py
chain_harvester/chainlink/mappings/optimism.py
chain_harvester/chainlink/mappings/polygon.py
chain_harvester/chainlink/mappings/scroll.py
chain_harvester/constants.py
chain_harvester/decoders.py
chain_harvester/exceptions.py
chain_harvester/helpers.py
chain_harvester/http.py
chain_harvester/merkle_proof.py
chain_harvester/message.py
chain_harvester/mixins.py
chain_harvester/multicall.py
chain_harvester/networks/__init__.py
chain_harvester/networks/arbitrum/__init__.py
chain_harvester/networks/arbitrum/mainnet.py
chain_harvester/networks/avalanche/__init__.py
chain_harvester/networks/avalanche/mainnet.py
chain_harvester/networks/base/__init__.py
chain_harvester/networks/base/mainnet.py
chain_harvester/networks/blast/__init__.py
chain_harvester/networks/blast/mainnet.py
chain_harvester/networks/ethereum/__init__.py
chain_harvester/networks/ethereum/mainnet.py
chain_harvester/networks/ethereum/sepolia.py
chain_harvester/networks/filecoin/__init__.py
chain_harvester/networks/filecoin/mainnet.py
chain_harvester/networks/gnosis/__init__.py
chain_harvester/networks/gnosis/mainnet.py
chain_harvester/networks/hemi/__init__.py
chain_harvester/networks/hemi/mainnet.py
chain_harvester/networks/hyperliquid/__init__.py
chain_harvester/networks/hyperliquid/mainnet.py
chain_harvester/networks/linea/__init__.py
chain_harvester-2.10.1.dist-info/LICENSE
chain_harvester-2.10.1.dist-info/METADATA
chain_harvester-2.10.1.dist-info/WHEEL
chain_harvester-2.10.1.dist-info/RECORD
