Metadata-Version: 2.1
Name: chain_harvester
Version: 2.10.1
Summary: A Python library designed to interface with various blockchain networks, enabling the retrieval of data.
Home-page: https://github.com/blockanalitica/chain-harvester
Author: 0xCommanderKeen
Author-email: f91289621+0xCommanderKeen@users.noreply.github.com
Requires-Python: >=3.11,<4.0
Classifier: Programming Language :: Python :: 3
Classifier: Programming Language :: Python :: 3.11
Classifier: Programming Language :: Python :: 3.12
Classifier: Programming Language :: Python :: 3.13
Requires-Dist: boto3 (>=1.40.33,<2.0.0)
Requires-Dist: eth-abi (>=5.1.0,<6.0.0)
Requires-Dist: multiproof (>=0.1.10,<0.2.0)
Requires-Dist: requests (>=2.31.0,<3.0.0)
Requires-Dist: web3 (>=7.7.0,<8.0.0)
Project-URL: Documentation, https://blockanalitica.github.io/chain-harvester/
Project-URL: Repository, https://github.com/blockanalitica/chain-harvester
